itkwasm_transform_wasi/__init__.py
itkwasm_transform_wasi/_version.py
itkwasm_transform_wasi/affine_ops.py
itkwasm_transform_wasi/create_affine_transform.py
itkwasm_transform_wasi/create_azimuth_elevation_to_cartesian_transform.py
itkwasm_transform_wasi/create_bspline_smoothing_on_update_displacement_field_transform.py
itkwasm_transform_wasi/create_bspline_transform.py
itkwasm_transform_wasi/create_composite_transform.py
itkwasm_transform_wasi/create_constant_velocity_field_transform.py
itkwasm_transform_wasi/create_displacement_field_transform.py
itkwasm_transform_wasi/create_euler2d_transform.py
itkwasm_transform_wasi/create_euler3d_transform.py
itkwasm_transform_wasi/create_gaussian_exponential_diffeomorphic_transform.py
itkwasm_transform_wasi/create_gaussian_smoothing_on_update_displacement_field_transform.py
itkwasm_transform_wasi/create_gaussian_smoothing_on_update_time_varying_velocity_field_transform.py
itkwasm_transform_wasi/create_identity_transform.py
itkwasm_transform_wasi/create_quaternion_rigid_transform.py
itkwasm_transform_wasi/create_rigid2d_transform.py
itkwasm_transform_wasi/create_rigid3d_perspective_transform.py
itkwasm_transform_wasi/create_rigid3d_transform.py
itkwasm_transform_wasi/create_scalable_affine_transform.py
itkwasm_transform_wasi/create_scale_logarithmic_transform.py
itkwasm_transform_wasi/create_scale_skew_versor3d_transform.py
itkwasm_transform_wasi/create_scale_transform.py
itkwasm_transform_wasi/create_similarity2d_transform.py
itkwasm_transform_wasi/create_similarity3d_transform.py
itkwasm_transform_wasi/create_time_varying_velocity_field_transform.py
itkwasm_transform_wasi/create_translation_transform.py
itkwasm_transform_wasi/create_velocity_field_transform.py
itkwasm_transform_wasi/create_versor_rigid3d_transform.py
itkwasm_transform_wasi/create_versor_transform.py
itkwasm_transform_wasi/wasm_modules/affine-ops.wasi.wasm
itkwasm_transform_wasi/wasm_modules/create-affine-transform.wasi.wasm
itkwasm_transform_wasi-0.1.0.dist-info/METADATA
itkwasm_transform_wasi-0.1.0.dist-info/WHEEL
itkwasm_transform_wasi-0.1.0.dist-info/RECORD
